odoo/addons/mrp_bom_multi_company/README.rst
odoo/addons/mrp_bom_multi_company/__init__.py
odoo/addons/mrp_bom_multi_company/__manifest__.py
odoo/addons/mrp_bom_multi_company/i18n/mrp_bom_multi_company.pot
odoo/addons/mrp_bom_multi_company/models/__init__.py
odoo/addons/mrp_bom_multi_company/models/mrp_bom.py
odoo/addons/mrp_bom_multi_company/static/description/icon.png
odoo12_addon_mrp_bom_multi_company-12.0.1.0.1.dist-info/METADATA
odoo12_addon_mrp_bom_multi_company-12.0.1.0.1.dist-info/WHEEL
odoo12_addon_mrp_bom_multi_company-12.0.1.0.1.dist-info/top_level.txt
odoo12_addon_mrp_bom_multi_company-12.0.1.0.1.dist-info/RECORD
